atc_mi_interface/__init__.py
atc_mi_interface/__main__.py
atc_mi_interface/__version__.py
atc_mi_interface/atc_mi_adv_format.py
atc_mi_interface/atc_mi_advertising.py
atc_mi_interface/atc_mi_config.py
atc_mi_interface/atc_mi_construct.py
atc_mi_interface/atc_mi_construct_adapters.py
atc_mi_interface/atc_mi_format_test.py
atc_mi_interface/construct_module.py
atc_mi_interface-2.0.0.dist-info/METADATA
atc_mi_interface-2.0.0.dist-info/WHEEL
atc_mi_interface-2.0.0.dist-info/entry_points.txt
atc_mi_interface-2.0.0.dist-info/top_level.txt
atc_mi_interface-2.0.0.dist-info/RECORD
