Metadata-Version: 2.1
Name: atc-mi-interface
Version: 2.0.0
Summary: Python tools and API for the "atc1441" and "pvvx" Xiaomi Mijia Thermometer custom firmware (ATC_MiThermometer)
Home-page: https://github.com/pvvx/ATC_MiThermometer/tree/master/python-interface
Author: Ircama
License: https://unlicense.org
Keywords: atc-mi-interface,Xiaomi,Mijia,Thermometer,firmware,wxpython,editor,construct,bleak,BLE,bluetooth,LYWSD03MMC
Classifier: License :: OSI Approved :: The Unlicense (Unlicense)
Classifier: Topic :: Software Development :: Libraries :: Python Modules
Classifier: Programming Language :: Python :: 3 :: Only
Classifier: Programming Language :: Python :: Implementation :: CPython
Classifier: Development Status :: 5 - Production/Stable
Classifier: Typing :: Typed
Classifier: Intended Audience :: Developers
Requires-Python: >=3.8
Requires-Dist: construct
Requires-Dist: bleak
Requires-Dist: pycryptodome
Requires-Dist: arrow
Provides-Extra: gui
Requires-Dist: wxPython ; extra == 'gui'
Requires-Dist: construct-gallery >=1.1.0 ; extra == 'gui'
Requires-Dist: construct-editor ; extra == 'gui'
